setup.cfg
setup.py
sqlalchemy_phoenix/__init__.py
sqlalchemy_phoenix/base.py
sqlalchemy_phoenix/jaydebeapidb.py
sqlalchemy_phoenix/phoenix_db.py
sqlalchemy_phoenix/requirements.py
sqlalchemy_phoenix/types.py
sqlalchemy_phoenix.egg-info/PKG-INFO
sqlalchemy_phoenix.egg-info/SOURCES.txt
sqlalchemy_phoenix.egg-info/dependency_links.txt
sqlalchemy_phoenix.egg-info/entry_points.txt
sqlalchemy_phoenix.egg-info/not-zip-safe
sqlalchemy_phoenix.egg-info/requires.txt
sqlalchemy_phoenix.egg-info/top_level.txt