Metadata-Version: 1.1
Name: sqlalchemy-phoenix
Version: 0.3.0
Summary: SQLAlchemy dialect for Phoenix
Home-page: UNKNOWN
Author: Dimitri Capitaine
Author-email: grytes29@gmail.com
License: MIT
Keywords: Phoenix SQLAlchemy
Platform: UNKNOWN
Classifier: Development Status :: 5 - Production/Stable
Classifier: Environment :: Console
Classifier: Intended Audience :: Developers
Classifier: Programming Language :: Python
Classifier: Programming Language :: Python :: 3
Classifier: Programming Language :: Python :: Implementation :: CPython
Classifier: Programming Language :: Python :: Implementation :: PyPy
Classifier: Topic :: Database :: Front-Ends
